combigraphs/__init__.py
combigraphs/combfuncs/__init__.py
combigraphs/combfuncs/comb.py
combigraphs/combfuncs/fact.py
combigraphs/combfuncs/place.py
combigraphs/graph/__init__.py
combigraphs/graph/builder.py
combigraphs/graph/cnt_routes_of_lenght_k_infull_graph.py
combigraphs/graph/cnt_subgraphs_of_size_k.py
combigraphs/graph/routes.py
combigraphs/graph/visualize.py
combigraphs-0.0.1.dist-info/licenses/LICENSE
combigraphs-0.0.1.dist-info/METADATA
combigraphs-0.0.1.dist-info/WHEEL
combigraphs-0.0.1.dist-info/top_level.txt
combigraphs-0.0.1.dist-info/RECORD
