Metadata-Version: 2.4
Name: combigraphs
Version: 0.0.1
Summary: Python - библиотека для комбинаторики и графов, а также их совместного использования для решения некоторых задач. Подробнее: https://github.com/hikrim/combigraphs/README.md
Author-email: Петлин Артём <1132246846@pfur.ru>
License-Expression: GPL-3.0-or-later
Project-URL: Homepage, https://github.com/hikrim/combigraphs
Project-URL: Issues, https://github.com/hikrim/combigraphs/issues
Classifier: Programming Language :: Python :: 3
Classifier: Operating System :: OS Independent
Requires-Python: >=3.9
License-File: LICENSE
Requires-Dist: matplotlib
Requires-Dist: networkx
Dynamic: license-file
